tobi/__init__.py
tobi/backend/EIT_class.py
tobi/protocol/Protocol.py
tobi/results/EIT_results.py
tobi/system/tomobimms.py
tobi/utils/constantsmux.py
tomoBIMMS-0.0.2.dist-info/METADATA
tomoBIMMS-0.0.2.dist-info/WHEEL
tomoBIMMS-0.0.2.dist-info/top_level.txt
tomoBIMMS-0.0.2.dist-info/RECORD
